README.rst
setup.cfg
setup.py
./__init__.py
./static_file.py
./tryton.cfg
./tests/__init__.py
./tests/test_static_file.py
trytond_nereid_image_transformation.egg-info/PKG-INFO
trytond_nereid_image_transformation.egg-info/SOURCES.txt
trytond_nereid_image_transformation.egg-info/dependency_links.txt
trytond_nereid_image_transformation.egg-info/entry_points.txt
trytond_nereid_image_transformation.egg-info/not-zip-safe
trytond_nereid_image_transformation.egg-info/requires.txt
trytond_nereid_image_transformation.egg-info/top_level.txt