Metadata-Version: 1.1
Name: trytond-nereid-image-transformation
Version: 3.4.0.1
Summary: Nereid Dynamic Image Resizing and transformation module
Home-page: http://openlabs.co.in
Author: Openlabs Technologies and Consulting (P) Ltd.
Author-email: UNKNOWN
License: UNKNOWN
Download-URL: https://github.com/openlabs/trytond-nereid-image-transformation
Platform: UNKNOWN
Classifier: Development Status :: 5 - Production/Stable
Classifier: Environment :: Plugins
Classifier: Framework :: Tryton
Classifier: Intended Audience :: Developers
Classifier: Intended Audience :: Financial and Insurance Industry
Classifier: Intended Audience :: Legal Industry
Classifier: Intended Audience :: Manufacturing
Classifier: License :: OSI Approved :: BSD License
Classifier: Natural Language :: English
Classifier: Operating System :: OS Independent
Classifier: Programming Language :: Python :: 2.6
Classifier: Programming Language :: Python :: 2.7
Classifier: Topic :: Office/Business
